botbuilder/adapters/slack/__init__.py
botbuilder/adapters/slack/about.py
botbuilder/adapters/slack/activity_resourceresponse.py
botbuilder/adapters/slack/slack_adapter.py
botbuilder/adapters/slack/slack_adatper_options.py
botbuilder/adapters/slack/slack_client.py
botbuilder/adapters/slack/slack_client_options.py
botbuilder/adapters/slack/slack_event.py
botbuilder/adapters/slack/slack_helper.py
botbuilder/adapters/slack/slack_message.py
botbuilder/adapters/slack/slack_payload.py
botbuilder/adapters/slack/slack_request_body.py
botbuilder_adapters_slack-4.17.1.dist-info/METADATA
botbuilder_adapters_slack-4.17.1.dist-info/WHEEL
botbuilder_adapters_slack-4.17.1.dist-info/top_level.txt
botbuilder_adapters_slack-4.17.1.dist-info/RECORD
