Metadata-Version: 2.1
Name: botbuilder-adapters-slack
Version: 4.17.1
Summary: Microsoft Bot Framework Bot Builder
Home-page: https://www.github.com/Microsoft/botbuilder-python
Author: Microsoft
License: MIT
Keywords: BotBuilderAdapters,bots,ai,botframework,botbuilder
Classifier: Programming Language :: Python :: 3.7
Classifier: Intended Audience :: Developers
Classifier: License :: OSI Approved :: MIT License
Classifier: Operating System :: OS Independent
Classifier: Development Status :: 5 - Production/Stable
Classifier: Topic :: Scientific/Engineering :: Artificial Intelligence
Requires-Dist: botbuilder-schema==4.17.1
Requires-Dist: botframework-connector==4.17.1
Requires-Dist: botbuilder-core==4.17.1
Requires-Dist: pyslack
Requires-Dist: slackclient
Requires-Dist: aiounittest==1.3.0
